wokki_chat_bot/__init__.py
wokki_chat_bot/client.py
wokki_chat_bot_client-0.2.3.dist-info/METADATA
wokki_chat_bot_client-0.2.3.dist-info/WHEEL
wokki_chat_bot_client-0.2.3.dist-info/top_level.txt
wokki_chat_bot_client-0.2.3.dist-info/RECORD
